{
  "date": "2023-08-30",
  "count": 75,
  "entries": [
    {
      "rank": 1,
      "missions": 3,
      "displayScore": 599,
      "timeSecs": 29,
      "timeStr": "0:29",
      "details": "3:0:99:29",
      "steamId": 76561197997854891,
      "name": "Durry Quill"
    },
    {
      "rank": 2,
      "missions": 3,
      "displayScore": 599,
      "timeSecs": 32,
      "timeStr": "0:32",
      "details": "3:0:99:32",
      "steamId": 76561198838007597,
      "name": "Seven-Two"
    },
    {
      "rank": 3,
      "missions": 3,
      "displayScore": 596,
      "timeSecs": 79,
      "timeStr": "1:19",
      "details": "3:0:96:79",
      "steamId": 76561197975901073,
      "name": "Kassandra"
    },
    {
      "rank": 4,
      "missions": 3,
      "displayScore": 596,
      "timeSecs": 81,
      "timeStr": "1:21",
      "details": "3:0:96:81",
      "steamId": 76561198052436469,
      "name": "Hekateras"
    },
    {
      "rank": 5,
      "missions": 3,
      "displayScore": 591,
      "timeSecs": 165,
      "timeStr": "2:45",
      "details": "3:0:91:165",
      "steamId": 76561198120436293,
      "name": "Tom Jackal"
    },
    {
      "rank": 6,
      "missions": 3,
      "displayScore": 590,
      "timeSecs": 193,
      "timeStr": "3:13",
      "details": "3:0:90:193",
      "steamId": 76561198001048776,
      "name": "Consigliere"
    },
    {
      "rank": 7,
      "missions": 3,
      "displayScore": 587,
      "timeSecs": 249,
      "timeStr": "4:09",
      "details": "3:0:87:249",
      "steamId": 76561198391141601,
      "name": "subvxrt"
    },
    {
      "rank": 8,
      "missions": 3,
      "displayScore": 586,
      "timeSecs": 269,
      "timeStr": "4:29",
      "details": "3:0:86:269",
      "steamId": 76561198069020786,
      "name": "frayser"
    },
    {
      "rank": 9,
      "missions": 3,
      "displayScore": 584,
      "timeSecs": 288,
      "timeStr": "4:48",
      "details": "3:0:84:288",
      "steamId": 76561197972912428,
      "name": "Darnn"
    },
    {
      "rank": 10,
      "missions": 3,
      "displayScore": 582,
      "timeSecs": 324,
      "timeStr": "5:24",
      "details": "3:0:82:324",
      "steamId": 76561198199073829,
      "name": "Nonka"
    },
    {
      "rank": 11,
      "missions": 3,
      "displayScore": 582,
      "timeSecs": 333,
      "timeStr": "5:33",
      "details": "3:0:82:333",
      "steamId": 76561197960689968,
      "name": "Talosity"
    },
    {
      "rank": 12,
      "missions": 3,
      "displayScore": 579,
      "timeSecs": 378,
      "timeStr": "6:18",
      "details": "3:0:79:378",
      "steamId": 76561198041958163,
      "name": "SickJ"
    },
    {
      "rank": 13,
      "missions": 3,
      "displayScore": 575,
      "timeSecs": 451,
      "timeStr": "7:31",
      "details": "3:0:75:451",
      "steamId": 76561198040173814,
      "name": "echo2878"
    },
    {
      "rank": 14,
      "missions": 3,
      "displayScore": 574,
      "timeSecs": 481,
      "timeStr": "8:01",
      "details": "3:0:74:481",
      "steamId": 76561198047021383,
      "name": "Rufus"
    },
    {
      "rank": 15,
      "missions": 3,
      "displayScore": 541,
      "timeSecs": 1078,
      "timeStr": "17:58",
      "details": "3:0:41:1078",
      "steamId": 76561197969560308,
      "name": "wlcrm"
    },
    {
      "rank": 16,
      "missions": 3,
      "displayScore": 540,
      "timeSecs": 1097,
      "timeStr": "18:17",
      "details": "3:0:40:1097",
      "steamId": 76561198064734641,
      "name": "Weabully"
    },
    {
      "rank": 17,
      "missions": 3,
      "displayScore": 487,
      "timeSecs": 481,
      "timeStr": "8:01",
      "details": "3:-13:0:481",
      "steamId": 76561198143267953,
      "name": "ZenoCarlos"
    },
    {
      "rank": 18,
      "missions": 3,
      "displayScore": 450,
      "timeSecs": 62,
      "timeStr": "1:02",
      "details": "3:0:-50:62",
      "steamId": 76561199445061518,
      "name": "heat-signature"
    },
    {
      "rank": 19,
      "missions": 3,
      "displayScore": 450,
      "timeSecs": 184,
      "timeStr": "3:04",
      "details": "3:0:-50:184",
      "steamId": 76561198028332942,
      "name": "t-cake"
    },
    {
      "rank": 20,
      "missions": 3,
      "displayScore": 450,
      "timeSecs": 207,
      "timeStr": "3:27",
      "details": "3:0:-50:207",
      "steamId": 76561197964141316,
      "name": "Rolan7 (She/her)"
    },
    {
      "rank": 21,
      "missions": 3,
      "displayScore": 450,
      "timeSecs": 225,
      "timeStr": "3:45",
      "details": "3:0:-50:225",
      "steamId": 76561198025397185,
      "name": "Unexpected"
    },
    {
      "rank": 22,
      "missions": 3,
      "displayScore": 450,
      "timeSecs": 351,
      "timeStr": "5:51",
      "details": "3:0:-50:351",
      "steamId": 76561198058404554,
      "name": "Undead_Knave"
    },
    {
      "rank": 23,
      "missions": 3,
      "displayScore": 450,
      "timeSecs": 467,
      "timeStr": "7:47",
      "details": "3:0:-50:467",
      "steamId": 76561198389249325,
      "name": "Donian"
    },
    {
      "rank": 24,
      "missions": 3,
      "displayScore": 450,
      "timeSecs": 544,
      "timeStr": "9:04",
      "details": "3:0:-50:544",
      "steamId": 76561198039769756,
      "name": "kwerboom"
    },
    {
      "rank": 25,
      "missions": 3,
      "displayScore": 450,
      "timeSecs": 911,
      "timeStr": "15:11",
      "details": "3:0:-50:911",
      "steamId": 76561198072996552,
      "name": "tjbwilson"
    },
    {
      "rank": 26,
      "missions": 3,
      "displayScore": 430,
      "timeSecs": 1599,
      "timeStr": "26:39",
      "details": "3:-20:-50:1599",
      "steamId": 76561198075007183,
      "name": "edibleturd"
    },
    {
      "rank": 27,
      "missions": 3,
      "displayScore": 425,
      "timeSecs": 716,
      "timeStr": "11:56",
      "details": "3:-25:-50:716",
      "steamId": 76561197972439152,
      "name": "kevinr"
    },
    {
      "rank": 28,
      "missions": 3,
      "displayScore": 400,
      "timeSecs": 444,
      "timeStr": "7:24",
      "details": "3:-50:-50:444",
      "steamId": 76561197974475925,
      "name": "GoogleyGareth"
    },
    {
      "rank": 29,
      "missions": 3,
      "displayScore": 400,
      "timeSecs": 618,
      "timeStr": "10:18",
      "details": "3:0:-100:618",
      "steamId": 76561198148394355,
      "name": "Neurotical Experience"
    },
    {
      "rank": 30,
      "missions": 3,
      "displayScore": 400,
      "timeSecs": 1387,
      "timeStr": "23:07",
      "details": "3:-100:0:1387",
      "steamId": 76561198031582687,
      "name": "Deathbycomma"
    },
    {
      "rank": 31,
      "missions": 3,
      "displayScore": 375,
      "timeSecs": 1544,
      "timeStr": "25:44",
      "details": "3:-75:-50:1544",
      "steamId": 76561198120239954,
      "name": "IkaTheFox"
    },
    {
      "rank": 32,
      "missions": 3,
      "displayScore": 275,
      "timeSecs": 557,
      "timeStr": "9:17",
      "details": "3:-75:-150:557",
      "steamId": 76561197995395763,
      "name": "hengis"
    },
    {
      "rank": 33,
      "missions": 3,
      "displayScore": 271,
      "timeSecs": 561,
      "timeStr": "9:21",
      "details": "3:-79:-150:561",
      "steamId": 76561198100907909,
      "name": "kitamuramiike"
    },
    {
      "rank": 34,
      "missions": 2,
      "displayScore": 250,
      "timeSecs": 130,
      "timeStr": "2:10",
      "details": "2:0:0:130",
      "steamId": 76561198316493324,
      "name": "LeeSpork"
    },
    {
      "rank": 35,
      "missions": 2,
      "displayScore": 250,
      "timeSecs": 278,
      "timeStr": "4:38",
      "details": "2:0:0:278",
      "steamId": 76561198018147681,
      "name": "Inky Bloc"
    },
    {
      "rank": 36,
      "missions": 2,
      "displayScore": 250,
      "timeSecs": 367,
      "timeStr": "6:07",
      "details": "2:0:0:367",
      "steamId": 76561197989814220,
      "name": "Arlechino212"
    },
    {
      "rank": 37,
      "missions": 2,
      "displayScore": 250,
      "timeSecs": 557,
      "timeStr": "9:17",
      "details": "2:0:0:557",
      "steamId": 76561198097727376,
      "name": "Nocturne"
    },
    {
      "rank": 38,
      "missions": 2,
      "displayScore": 250,
      "timeSecs": 687,
      "timeStr": "11:27",
      "details": "2:0:0:687",
      "steamId": 76561197991759715,
      "name": "Random Acts of Panda"
    },
    {
      "rank": 39,
      "missions": 3,
      "displayScore": 234,
      "timeSecs": 1345,
      "timeStr": "22:25",
      "details": "3:-116:-150:1345",
      "steamId": 76561198078909833,
      "name": "martinsa"
    },
    {
      "rank": 40,
      "missions": 3,
      "displayScore": 225,
      "timeSecs": 455,
      "timeStr": "7:35",
      "details": "3:-125:-150:455",
      "steamId": 76561198041743047,
      "name": "Bossofhalo"
    },
    {
      "rank": 41,
      "missions": 2,
      "displayScore": 200,
      "timeSecs": 183,
      "timeStr": "3:03",
      "details": "2:0:-50:183",
      "steamId": 76561198125028523,
      "name": "Munter"
    },
    {
      "rank": 42,
      "missions": 2,
      "displayScore": 200,
      "timeSecs": 489,
      "timeStr": "8:09",
      "details": "2:0:-50:489",
      "steamId": 76561199007762220,
      "name": "Anton64"
    },
    {
      "rank": 43,
      "missions": 2,
      "displayScore": 200,
      "timeSecs": 727,
      "timeStr": "12:07",
      "details": "2:0:-50:727",
      "steamId": 76561198004760355,
      "name": "Zarifas"
    },
    {
      "rank": 44,
      "missions": 3,
      "displayScore": 170,
      "timeSecs": 368,
      "timeStr": "6:08",
      "details": "3:-180:-150:368",
      "steamId": 76561198075039845,
      "name": "Rouce"
    },
    {
      "rank": 45,
      "missions": 2,
      "displayScore": 150,
      "timeSecs": 446,
      "timeStr": "7:26",
      "details": "2:0:-100:446",
      "steamId": 76561198330424563,
      "name": "Jeru666"
    },
    {
      "rank": 46,
      "missions": 2,
      "displayScore": 150,
      "timeSecs": 874,
      "timeStr": "14:34",
      "details": "2:0:-100:874",
      "steamId": 76561198009479075,
      "name": "Myrk"
    },
    {
      "rank": 47,
      "missions": 2,
      "displayScore": 125,
      "timeSecs": 733,
      "timeStr": "12:13",
      "details": "2:-75:-50:733",
      "steamId": 76561197992442212,
      "name": "[d20] Pibald"
    },
    {
      "rank": 48,
      "missions": 2,
      "displayScore": 125,
      "timeSecs": 819,
      "timeStr": "13:39",
      "details": "2:-25:-100:819",
      "steamId": 76561198112036898,
      "name": "GospodinGovnyk"
    },
    {
      "rank": 49,
      "missions": 2,
      "displayScore": 100,
      "timeSecs": 558,
      "timeStr": "9:18",
      "details": "2:-50:-100:558",
      "steamId": 76561197972315260,
      "name": "bushwhacker666"
    },
    {
      "rank": 50,
      "missions": 2,
      "displayScore": 100,
      "timeSecs": 1056,
      "timeStr": "17:36",
      "details": "2:-100:-50:1056",
      "steamId": 76561198097729804,
      "name": "Dawn"
    },
    {
      "rank": 51,
      "missions": 1,
      "displayScore": 100,
      "timeSecs": 576,
      "timeStr": "9:36",
      "details": "1:0:0:576",
      "steamId": 76561198108845373,
      "name": "ian.simcock"
    },
    {
      "rank": 52,
      "missions": 1,
      "displayScore": 50,
      "timeSecs": 757,
      "timeStr": "12:37",
      "details": "1:0:-50:757",
      "steamId": 76561198067851126,
      "name": "Dread Baron Beardly"
    },
    {
      "rank": 53,
      "missions": 1,
      "displayScore": 50,
      "timeSecs": 874,
      "timeStr": "14:34",
      "details": "1:0:-50:874",
      "steamId": 76561198089248141,
      "name": "Sonic-Claw 17"
    },
    {
      "rank": 54,
      "missions": 1,
      "displayScore": 50,
      "timeSecs": 1028,
      "timeStr": "17:08",
      "details": "1:0:-50:1028",
      "steamId": 76561198259521915,
      "name": "inflictedcircle"
    },
    {
      "rank": 55,
      "missions": 1,
      "displayScore": 30,
      "timeSecs": 970,
      "timeStr": "16:10",
      "details": "1:-20:-50:970",
      "steamId": 76561198146085455,
      "name": "PrinnyLazyDood"
    },
    {
      "rank": 56,
      "missions": 0,
      "displayScore": 0,
      "timeSecs": 14,
      "timeStr": "0:14",
      "details": "0:0:0:14",
      "steamId": 76561198802032417,
      "name": "altlaw"
    },
    {
      "rank": 57,
      "missions": 0,
      "displayScore": 0,
      "timeSecs": 73,
      "timeStr": "1:13",
      "details": "0:0:0:73",
      "steamId": 76561198407480033,
      "name": "det.maginer"
    },
    {
      "rank": 58,
      "missions": 0,
      "displayScore": 0,
      "timeSecs": 83,
      "timeStr": "1:23",
      "details": "0:0:0:83",
      "steamId": 76561199248459476,
      "name": "happemstance"
    },
    {
      "rank": 59,
      "missions": 0,
      "displayScore": 0,
      "timeSecs": 86,
      "timeStr": "1:26",
      "details": "0:0:0:86",
      "steamId": 76561198273300525,
      "name": "jameslelnen"
    },
    {
      "rank": 60,
      "missions": 0,
      "displayScore": 0,
      "timeSecs": 88,
      "timeStr": "1:28",
      "details": "0:0:0:88",
      "steamId": 76561198059522075,
      "name": "Adam Bandt"
    },
    {
      "rank": 61,
      "missions": 0,
      "displayScore": 0,
      "timeSecs": 97,
      "timeStr": "1:37",
      "details": "0:0:0:97",
      "steamId": 76561199225533940,
      "name": "Marinko"
    },
    {
      "rank": 62,
      "missions": 0,
      "displayScore": 0,
      "timeSecs": 104,
      "timeStr": "1:44",
      "details": "0:0:0:104",
      "steamId": 76561197979612737,
      "name": "bosoxbill"
    },
    {
      "rank": 63,
      "missions": 0,
      "displayScore": 0,
      "timeSecs": 115,
      "timeStr": "1:55",
      "details": "0:0:0:115",
      "steamId": 76561198275799902,
      "name": "bernhard.muhr"
    },
    {
      "rank": 64,
      "missions": 0,
      "displayScore": 0,
      "timeSecs": 144,
      "timeStr": "2:24",
      "details": "0:0:0:144",
      "steamId": 76561197962036544,
      "name": "London Prophet"
    },
    {
      "rank": 65,
      "missions": 0,
      "displayScore": 0,
      "timeSecs": 160,
      "timeStr": "2:40",
      "details": "0:0:0:160",
      "steamId": 76561198122781989,
      "name": "ScOwOby"
    },
    {
      "rank": 66,
      "missions": 0,
      "displayScore": 0,
      "timeSecs": 213,
      "timeStr": "3:33",
      "details": "0:0:0:213",
      "steamId": 76561198967333429,
      "name": "adeus"
    },
    {
      "rank": 66,
      "missions": 0,
      "displayScore": 0,
      "timeSecs": 213,
      "timeStr": "3:33",
      "details": "0:0:0:213",
      "steamId": 76561198054427152,
      "name": "Iskander the Adequate"
    },
    {
      "rank": 68,
      "missions": 0,
      "displayScore": 0,
      "timeSecs": 288,
      "timeStr": "4:48",
      "details": "0:0:0:288",
      "steamId": 76561198797743354,
      "name": "kibijosh"
    },
    {
      "rank": 69,
      "missions": 0,
      "displayScore": 0,
      "timeSecs": 302,
      "timeStr": "5:02",
      "details": "0:0:0:302",
      "steamId": 76561198189948158,
      "name": "valdimar2209"
    },
    {
      "rank": 70,
      "missions": 0,
      "displayScore": 0,
      "timeSecs": 303,
      "timeStr": "5:03",
      "details": "0:0:0:303",
      "steamId": 76561198192114637,
      "name": "Sopuyy"
    },
    {
      "rank": 71,
      "missions": -97,
      "displayScore": -9,
      "timeSecs": 10591,
      "timeStr": "176:31",
      "details": "2:-210:-50:591",
      "steamId": 76561198312853336,
      "name": "Ethanuel"
    },
    {
      "rank": 72,
      "missions": -99,
      "displayScore": -74,
      "timeSecs": 10341,
      "timeStr": "172:21",
      "details": "0:-75:0:341",
      "steamId": 76561198146256531,
      "name": "elwen"
    },
    {
      "rank": 73,
      "missions": -99,
      "displayScore": -74,
      "timeSecs": 11747,
      "timeStr": "195:47",
      "details": "0:-75:0:1747",
      "steamId": 76561197995320650,
      "name": "Yaant"
    },
    {
      "rank": 74,
      "missions": -97,
      "displayScore": -84,
      "timeSecs": 10320,
      "timeStr": "172:00",
      "details": "2:-235:-100:320",
      "steamId": 76561198101343227,
      "name": "Divided"
    },
    {
      "rank": 75,
      "missions": -98,
      "displayScore": -259,
      "timeSecs": 11443,
      "timeStr": "190:43",
      "details": "1:-310:-50:1443",
      "steamId": 76561198136374812,
      "name": "\u7A46\u7F55\u7A46\u5FB7\u00B7\u5C16\u53EB\u8005"
    }
  ]
}